seevars/__init__.py
seevars/show.py
seevars-0.1.1.dist-info/LICENSE
seevars-0.1.1.dist-info/METADATA
seevars-0.1.1.dist-info/WHEEL
seevars-0.1.1.dist-info/top_level.txt
seevars-0.1.1.dist-info/RECORD
